[
  {
    "name": "",
    "id": "",
    "date": "",
    "major": "ENGLBA ENLITR",
    "policies": "\u2022 Refer to the SU catalog for approved prerequisites and General Education courses. \n\u2022 All graduates must have a minimum of 120 credits.\n\u2022 All graduates must have a minimum of 30 credits of 300\/400-level courses with C grade or above; at least 15 of those credits must be taken at SU.\n\u2022 Students must have a minimum cumulative GPA of 2.0 for graduation.\n\u2022 Students must complete at least 30 credit hours by direct classroom instruction and\/or laboratory experience.\n\u2022 Students must take 30 of the last 37 credit hours at SU.\n\u2022 \u24b7 indicates the recommended minimum grade; although a C meets the requirement, SU history shows that students who graduate with this major earned this grade or higher for this course.",
    "semester_1": [
      {
        "subject": "ENGL",
        "catalog": "103B",
        "title": "Composition and Research",
        "credits": "4"
      },
      {
        "subject": "FTWL",
        "catalog": "106",
        "title": "Lifelong Fitness and Wellness",
        "credits": "3"
      },
      {
        "subject": "IIIA",
        "catalog": "",
        "title": "Gen Ed Humanities course",
        "credits": "4"
      },
      {
        "subject": "IVA",
        "catalog": "",
        "title": "Gen Ed Lab Science course",
        "credits": "4"
      }
    ],
    "semester_2": [
      {
        "subject": "ENGL",
        "catalog": "3XX",
        "title": "British\/American Literature course (1 of 3)",
        "credits": "4"
      },
      {
        "subject": "",
        "catalog": "",
        "title": "(ENGL 356, 357, 380 or 381)",
        "credits": ""
      },
      {
        "subject": "HIST",
        "catalog": "10XB",
        "title": "Gen Ed IIA (HIST 101, 102 or 103)",
        "credits": "4"
      },
      {
        "subject": "IVC",
        "catalog": "",
        "title": "Gen Ed Math course",
        "credits": "3-4"
      },
      {
        "subject": "Elective",
        "catalog": "",
        "title": "Needed for 120 credits",
        "credits": "3-4"
      }
    ],
    "semester_3": [
      {
        "subject": "ENGL",
        "catalog": "411",
        "title": "Chaucer\u2019s Visions and Voyages",
        "credits": "4"
      },
      {
        "subject": "ENGL",
        "catalog": "412",
        "title": "Milton\u2019s Angels and Demons",
        "credits": "4"
      },
      {
        "subject": "ENGL",
        "catalog": "413",
        "title": "Shakespeare",
        "credits": "4"
      },
      {
        "subject": "HIST",
        "catalog": "XXX",
        "title": "Gen Ed IIB History course",
        "credits": "4"
      },
      {
        "subject": "IVB",
        "catalog": "",
        "title": "Gen Ed Non-Lab Science or Math course",
        "credits": "3-4"
      },
      {
        "subject": "Language",
        "catalog": "",
        "title": "Fulton School Language requirement (if needed)",
        "credits": "4"
      }
    ],
    "semester_4": [
      {
        "subject": "ENGL",
        "catalog": "3XX",
        "title": "British\/American Literature course (2 of 3)",
        "credits": "4"
      },
      {
        "subject": "",
        "catalog": "",
        "title": "(ENGL 356, 357, 380 or 381)",
        "credits": ""
      },
      {
        "subject": "ENGL",
        "catalog": "XXX",
        "title": "Literature course (1 of 4)",
        "credits": "4"
      },
      {
        "subject": "Language",
        "catalog": "",
        "title": "Fulton School Language requirement (if needed)",
        "credits": "4"
      },
      {
        "subject": "Elective",
        "catalog": "",
        "title": "Needed for 120 credits",
        "credits": "3-4"
      }
    ],
    "semester_5": [
      {
        "subject": "ENGL",
        "catalog": "3XX",
        "title": "British\/American Literature course (3 of 3)",
        "credits": "4"
      },
      {
        "subject": "",
        "catalog": "",
        "title": "(ENGL 356, 357, 380 or 381)",
        "credits": ""
      },
      {
        "subject": "IIIB",
        "catalog": "",
        "title": "Gen Ed Social Science course",
        "credits": "3-4"
      },
      {
        "subject": "IVA",
        "catalog": "",
        "title": "Gen Ed Lab Science course",
        "credits": "4"
      },
      {
        "subject": "Elective",
        "catalog": "",
        "title": "Needed for 120 credits",
        "credits": "3-4"
      }
    ],
    "semester_6": [
      {
        "subject": "ENGL",
        "catalog": "3XX",
        "title": "British\/American Literature course (3 of 3)",
        "credits": "4"
      },
      {
        "subject": "",
        "catalog": "",
        "title": "(ENGL 356, 357, 380 or 381)",
        "credits": ""
      },
      {
        "subject": "IIIB",
        "catalog": "",
        "title": "Gen Ed Social Science course",
        "credits": "3-4"
      },
      {
        "subject": "IVA",
        "catalog": "",
        "title": "Gen Ed Lab Science course",
        "credits": "4"
      },
      {
        "subject": "Elective",
        "catalog": "",
        "title": "Needed for 120 credits",
        "credits": "3-4"
      }
    ],
    "semester_7": [
      {
        "subject": "ENGL",
        "catalog": "XXX",
        "title": "Writing course",
        "credits": "4"
      },
      {
        "subject": "",
        "catalog": "",
        "title": "(ENGL 306, 308, 463 or 464)",
        "credits": ""
      },
      {
        "subject": "ENGL",
        "catalog": "XXX",
        "title": "Literature course (3 of 4)",
        "credits": "4"
      },
      {
        "subject": "Elective",
        "catalog": "",
        "title": "Needed for 120 credits",
        "credits": "3-4"
      },
      {
        "subject": "Elective",
        "catalog": "",
        "title": "Needed for 120 credits",
        "credits": "3-4"
      }
    ],
    "semester_8": [
      {
        "subject": "ENGL",
        "catalog": "XXX",
        "title": "Diversity course",
        "credits": "4"
      },
      {
        "subject": "",
        "catalog": "",
        "title": "(ENGL 255, 256, 257, 258, 338, 365, 371, 377, 378",
        "credits": ", 379,"
      },
      {
        "subject": "",
        "catalog": "",
        "title": "382, 383, 384, 389, 469, 470)",
        "credits": ""
      },
      {
        "subject": "ENGL",
        "catalog": "XXX",
        "title": "Literature course (4 of 4)",
        "credits": "4"
      },
      {
        "subject": "Elective",
        "catalog": "",
        "title": "Needed for 120 credits",
        "credits": "3-4"
      },
      {
        "subject": "Elective",
        "catalog": "",
        "title": "If needed for 120 credits",
        "credits": "3-4"
      }
    ]
  }
]