[
  {
    "minor": "SPANMIN",
    "university_policies": "Salisbury University minors require:\n\u2022 The completion of at least 18 credits with grades of C or better.\n\u2022 At least 15 credits applied toward the minor must be coursework that is not used to\nsatisfy General Education requirements.\n\u2022 At least nine credits must be earned at SU.",
    "minor_req": "\u2022 Complete the recommended sequence for 5 courses.\n\u2022 Earn a grade of C or better in language courses taken toward the minor.\n\u2022 Only 1 course of the minor may be used to satisfy General Education requirements.\n\u2022 A maximum of 8 credits of transfer or examination credit may be used for the minor.\n\u2022 Complete the Minor Form and give it to Dr. Corinne Pubill.",
    "req_1": "Complete the following courses:",
    "course_1": [
      {
        "subject": "SPAN",
        "catalog": "202",
        "title": "Spanish in Review",
        "credits": "4"
      },
      {
        "subject": "SPAN",
        "catalog": "310",
        "title": "Oral and Written Composition",
        "credits": "4"
      },
      {
        "subject": "SPAN",
        "catalog": "313",
        "title": "Effective Reading and Writing",
        "credits": ""
      },
      {
        "subject": "SPAN",
        "catalog": "315",
        "title": "Spanish Culture and Civilization",
        "credits": "4"
      },
      {
        "subject": "SPAN",
        "catalog": "316",
        "title": "Latin American Culture and Civilization",
        "credits": "4"
      },
      {
        "subject": "SPAN",
        "catalog": "335",
        "title": "Survey of Spanish Literature",
        "credits": "4"
      },
      {
        "subject": "SPAN",
        "catalog": "336",
        "title": "Survey of Latin American Literature",
        "credits": "4"
      }
    ]
  }
]